README.md
setup.py
uttl/__init__.py
uttl.buildout.egg-info/PKG-INFO
uttl.buildout.egg-info/SOURCES.txt
uttl.buildout.egg-info/dependency_links.txt
uttl.buildout.egg-info/entry_points.txt
uttl.buildout.egg-info/namespace_packages.txt
uttl.buildout.egg-info/not-zip-safe
uttl.buildout.egg-info/requires.txt
uttl.buildout.egg-info/top_level.txt
uttl/buildout/__init__.py
uttl/buildout/base_recipe.py
uttl/buildout/command_recipe.py
uttl/buildout/cmake/__init__.py
uttl/buildout/cmake/cmake_recipe.py
uttl/buildout/copyfile/__init__.py
uttl/buildout/copyfile/copyfile_recipe.py
uttl/buildout/devenv/__init__.py
uttl/buildout/devenv/devenv_recipe.py
uttl/buildout/dotnet/__init__.py
uttl/buildout/dotnet/dotnet_recipe.py
uttl/buildout/dotnet/restore/__init__.py
uttl/buildout/dotnet/restore/dotnet_restore_recipe.py
uttl/buildout/inklecate/__init__.py
uttl/buildout/inklecate/inklecate_recipe.py
uttl/buildout/qmake/__init__.py
uttl/buildout/qmake/qmake_recipe.py
uttl/buildout/qtdeploy/__init__.py
uttl/buildout/qtdeploy/qtdeploy_recipe.py
uttl/buildout/versioncheck/__init__.py
uttl/buildout/versioncheck/versioncheck_recipe.py
uttl/buildout/vswhere/__init__.py
uttl/buildout/vswhere/vswhere_recipe.py