Metadata-Version: 2.1
Name: uttl.buildout
Version: 1.3.1
Summary: Utilities for Buildout developed for Up There They Love.
Home-page: https://github.com/MrHands/uttl-buildout
Author: Mr. Hands
Author-email: mrhands31@gmail.com
License: MIT-0
Keywords: buildout extension uttl cmake qmake qt copyfile version
Platform: UNKNOWN
Classifier: Framework :: Buildout
Classifier: Intended Audience :: Developers
Classifier: Topic :: Software Development :: Build Tools
Classifier: License :: OSI Approved :: MIT No Attribution License (MIT-0)
Requires-Python: >=3
